rdu/__init__.py
rdu/mol.py
rdu/rxn.py
rdu-0.0.1.dist-info/METADATA
rdu-0.0.1.dist-info/WHEEL
rdu-0.0.1.dist-info/entry_points.txt
rdu-0.0.1.dist-info/top_level.txt
rdu-0.0.1.dist-info/RECORD
