Metadata-Version: 2.1
Name: rdu
Version: 0.0.1
Summary: reaction data utils
Home-page: UNKNOWN
Author: zbc
Author-email: zbc@mail.ustc.edu.cn
License: UNKNOWN
Platform: UNKNOWN
Classifier: Programming Language :: Python :: 3
Classifier: License :: OSI Approved :: MIT License
Classifier: Operating System :: OS Independent
Requires-Python: >=3.6
Requires-Dist: pandas
